cdshealpix-0.7.2.dist-info/METADATA
cdshealpix-0.7.2.dist-info/WHEEL
cdshealpix-0.7.2.dist-info/licenses/LICENSE
cdshealpix/__init__.py
cdshealpix/cdshealpix.cpython-310-aarch64-linux-gnu.so
cdshealpix/nested/__init__.py
cdshealpix/nested/healpix.py
cdshealpix/ring/__init__.py
cdshealpix/ring/healpix.py
cdshealpix/skymap/__init__.py
cdshealpix/skymap/skymap.py
cdshealpix/tests/__init__.py
cdshealpix/tests/moc_coords.npy
cdshealpix/tests/resources/skymap.fits
cdshealpix/tests/test_benchmark_healpix.py
cdshealpix/tests/test_nested_healpix.py
cdshealpix/tests/test_ring_healpix.py
cdshealpix/tests/test_skymaps.py
cdshealpix/utils.py
cdshealpix/version.py
cdshealpix-0.7.2.dist-info/RECORD
