Metadata-Version: 2.4
Name: cdshealpix
Version: 0.7.2
Classifier: Programming Language :: Rust
Classifier: Programming Language :: Python :: 3.8
Classifier: Programming Language :: Python :: 3.9
Classifier: Programming Language :: Python :: 3.10
Classifier: Programming Language :: Python :: 3.11
Classifier: Programming Language :: Python :: 3.12
Requires-Dist: astropy<5.3 ; python_full_version == '3.8.*'
Requires-Dist: astropy ; python_full_version >= '3.9'
Requires-Dist: matplotlib ; extra == 'plot'
Provides-Extra: plot
License-File: LICENSE
Summary: A healpix manipulation library.
Keywords: astronomy,healpix
Home-Page: https://github.com/cds-astro/cds-healpix-python
Requires-Python: >=3.8
Project-URL: repository, https://github.com/cds-astro/cds-healpix-python
Project-URL: documentation, https://cds-astro.github.io/cds-healpix-python/
Project-URL: issues, https://github.com/cds-astro/cds-healpix-python/issues
Project-URL: changelog, https://github.com/cds-astro/cds-healpix-python/blob/master/CHANGELOG.md
